app/__init__.py
app/cli.py
app/commands/__init__.py
app/commands/base.py
app/commands/d.py
app/commands/destroy.py
app/commands/g.py
app/commands/generate.py
app/commands/hello.py
app/commands/i.py
app/commands/install.py
app/commands/new.py
app/commands/r.py
app/commands/run.py
app/commands/s.py
app/commands/scrap.py
app/commands/send.py
app/commands/serve.py
app/commands/simulate.py
app/commands/t.py
app/commands/test.py
app/commands/u.py
app/commands/update.py
app/templates/Gemfile
app/templates/README.md
app/templates/app/type.jl
app/templates/config/application.jl
app/templates/config/export_all_except.jl
app/templates/config/include_all.jl
app/templates/test/test_helper.jl
app/templates/test/type_test.jl
julz-1.0.3.dist-info/DESCRIPTION.rst
julz-1.0.3.dist-info/METADATA
julz-1.0.3.dist-info/RECORD
julz-1.0.3.dist-info/WHEEL
julz-1.0.3.dist-info/entry_points.txt
julz-1.0.3.dist-info/metadata.json
julz-1.0.3.dist-info/top_level.txt
